RoboticsLanguage/.DS_Store
RoboticsLanguage/__init__.py
RoboticsLanguage/__init__.pyc
RoboticsLanguage/Base/CommandLine.py
RoboticsLanguage/Base/CommandLine.pyc
RoboticsLanguage/Base/Initialise.py
RoboticsLanguage/Base/Initialise.pyc
RoboticsLanguage/Base/Inputs.py
RoboticsLanguage/Base/Inputs.pyc
RoboticsLanguage/Base/Outputs.py
RoboticsLanguage/Base/Outputs.pyc
RoboticsLanguage/Base/Parameters.py
RoboticsLanguage/Base/Parameters.pyc
RoboticsLanguage/Base/Transformations.py
RoboticsLanguage/Base/Transformations.pyc
RoboticsLanguage/Base/Types.py
RoboticsLanguage/Base/Types.pyc
RoboticsLanguage/Base/Utilities.py
RoboticsLanguage/Base/Utilities.pyc
RoboticsLanguage/Base/__init__.py
RoboticsLanguage/Base/__init__.pyc
RoboticsLanguage/Base/Tests/__init__.py
RoboticsLanguage/Base/Tests/__init__.pyc
RoboticsLanguage/Base/Tests/test_base_commandline.py
RoboticsLanguage/Base/Tests/test_base_commandline.pyc
RoboticsLanguage/Base/Tests/test_base_transformations.py
RoboticsLanguage/Base/Tests/test_base_transformations.pyc
RoboticsLanguage/Base/Tests/test_base_utilities.py
RoboticsLanguage/Base/Tests/test_base_utilities.pyc
RoboticsLanguage/Base/Tools/ErrorHandling.py
RoboticsLanguage/Base/Tools/ErrorHandling.pyc
RoboticsLanguage/Base/Tools/__init__.py
RoboticsLanguage/Base/Tools/__init__.pyc
RoboticsLanguage/Base/Tools/test_templates.py
RoboticsLanguage/Base/Tools/test_templates.pyc
RoboticsLanguage/Documentation/README.md
RoboticsLanguage/Documentation/Assets/FiniteStateMachine.png
RoboticsLanguage/Documentation/Assets/TemporalLogic.png
RoboticsLanguage/Documentation/Assets/compiler-flow.png
RoboticsLanguage/Documentation/Assets/rol-logo.pdf
RoboticsLanguage/Documentation/Assets/rol-logo.png
RoboticsLanguage/Documentation/Assets/rol-logo.svg
RoboticsLanguage/Documentation/Compiler/Philosophy/README.md
RoboticsLanguage/Documentation/Compiler/Reference/.gitignore
RoboticsLanguage/Documentation/Compiler/Reference/README.md
RoboticsLanguage-0.3.26.dist-info/DESCRIPTION.rst
RoboticsLanguage-0.3.26.dist-info/METADATA
RoboticsLanguage-0.3.26.dist-info/RECORD
RoboticsLanguage-0.3.26.dist-info/WHEEL
RoboticsLanguage-0.3.26.dist-info/metadata.json
RoboticsLanguage-0.3.26.dist-info/top_level.txt
